{"otherData": {},"traceEvents":[{"cat":"function","dur":33714,"name":"__cdecl flame::OpenGLTexture2D::~OpenGLTexture2D(void)","ph":"X","pid":0,"tid":1392133180,"ts":159090678922},{"cat":"function","dur":3,"name":"__cdecl flame::OpenGLShader::~OpenGLShader(void)","ph":"X","pid":0,"tid":1392133180,"ts":159090712891},{"cat":"function","dur":6,"name":"__cdecl flame::OpenGLVertexArray::~OpenGLVertexArray(void)","ph":"X","pid":0,"tid":1392133180,"ts":159090713064},{"cat":"function","dur":18,"name":"__cdecl flame::OpenGLIndexBuffer::~OpenGLIndexBuffer(void)","ph":"X","pid":0,"tid":1392133180,"ts":159090713210},{"cat":"function","dur":5,"name":"__cdecl flame::OpenGLVertexBuffer::~OpenGLVertexBuffer(void)","ph":"X","pid":0,"tid":1392133180,"ts":159090713377},{"cat":"function","dur":34610,"name":"void __cdecl flame::Renderer2D::Shutdown(void)","ph":"X","pid":0,"tid":1392133180,"ts":159090678916},{"cat":"function","dur":34744,"name":"void __cdecl flame::Renderer::Shutdown(void)","ph":"X","pid":0,"tid":1392133180,"ts":159090678912},{"cat":"function","dur":34875,"name":"__cdecl flame::Application::~Application(void)","ph":"X","pid":0,"tid":1392133180,"ts":159090678908},{"cat":"function","dur":28,"name":"__cdecl flame::OpenGLTexture2D::~OpenGLTexture2D(void)","ph":"X","pid":0,"tid":1392133180,"ts":159090713917},{"cat":"function","dur":43153,"name":"void __cdecl flame::WindowsWindow::Shutdown(void)","ph":"X","pid":0,"tid":1392133180,"ts":159090714100},{"cat":"function","dur":43290,"name":"__cdecl flame::WindowsWindow::~WindowsWindow(void)","ph":"X","pid":0,"tid":1392133180,"ts":159090714096}]}